azcam_archon/__init__.py
azcam_archon/console_archon.py
azcam_archon/controller_archon.py
azcam_archon/exposure_archon.py
azcam_archon/tempcon_archon.py
azcam_archon-22.3.2.dist-info/LICENSE
azcam_archon-22.3.2.dist-info/WHEEL
azcam_archon-22.3.2.dist-info/METADATA
azcam_archon-22.3.2.dist-info/RECORD
