Metadata-Version: 2.1
Name: azcam-archon
Version: 22.3.2
Summary: Azcam extension for Semiconductor Technology Associates (STA) Archon controllers
Keywords: ccd,imaging,astronomy,sensors
Author: Michael Lesser
Author-email: mlesser@arizona.edu
Requires-Dist: azcam
Project-URL: Documentation, https://mplesser.github.io/azcam/
Project-URL: Repository, https://github.com/mplesser/azcam-archon/
